base_mlflow_model/__init__.py
base_mlflow_model/base_mlflow_model.py
mlflow_solar_boilerplate-0.0.3.dist-info/METADATA
mlflow_solar_boilerplate-0.0.3.dist-info/WHEEL
mlflow_solar_boilerplate-0.0.3.dist-info/top_level.txt
mlflow_solar_boilerplate-0.0.3.dist-info/RECORD
