Metadata-Version: 2.1
Name: mlflow-solar-boilerplate
Version: 0.0.3
Summary: base mlflow based package to automate model deployment for SOLAR project
Home-page: https://github.com/spavlyuk80/solar-mlflow-boilerplate
Author: Sergiy Pavlyuk
Author-email: s.pavlyuk@gmail.com
License: UNKNOWN
Platform: UNKNOWN
Classifier: Programming Language :: Python :: 3
Classifier: License :: OSI Approved :: MIT License
Classifier: Operating System :: OS Independent
Requires-Python: >=3.6
